{
	"stfFile":"spacequest/space_mining_destroy/restuss_imperial_lok_mining_1",
	"entries": {
		"assigned_delayed":"",	"autorewardbody":"",	"autorewardfrom":"",	"autorewardsubject":"",	"quest_location_d":"",	"quest_location_t":"",	"quest_mine_d":"",	"quest_mine_t":"",	"split_quest_alert":"",	"split_quest_alert_fail":"",	"title":"War preparations",	"title_d":"The Imperial Army requires raw materials to finish the defense base in Restuss. They have ordered you to supply them with 500 Obsidian ore from the Kessel system."
}}