{
	"stfFile":"quest/ground/recovery_quest_imperial_02",
	"entries": {
		"category":"Empire Day",	"journal_entry_completion_summary":"You have successfully rescued the first Imperial Officer from the Rebel Detainment Facility.",	"journal_entry_description":"Go to the Rebel Detainment Facility and rescue the first Imperial Officer being held prisoner.",	"journal_entry_title":"Rescue the first Imperial Officer",	"task00_journal_entry_description":"Go back to the Detainment Facility at the Rebel Hideout on Corellia.",	"task00_journal_entry_title":"Go back to the Detainment Facility",	"task00_waypoint_name":"Detainment Facility",	"task01_journal_entry_description":"Defeat Jorel Sherrol in combat and take his Rebel Trooper Armor.",	"task01_journal_entry_title":"Get the disguise from Jorel Sherrol",	"task02_journal_entry_description":"Destroy the Blastromech near the Detainment Center entrance.",	"task02_journal_entry_title":"Take out a Blastromech",	"task03_journal_entry_description":"Defeat Rebel Commandos guarding to the Rebel Detention Center.",	"task03_journal_entry_title":"Take out Rebel Commandos",	"task04_journal_entry_description":"n",	"task04_journal_entry_title":"n",	"task04_task_display_string_1":"task1",	"task04_task_display_string_2":"task2",	"task04_task_display_string_3":"task3",	"task05_comm_message_text":"I've sliced Sherrol's datapad and now we have a basic idea where all 6 of the prisoners are being held.  Great work.",	"task05_journal_entry_description":"n",	"task05_journal_entry_title":"n",	"task06_journal_entry_description":"Search the holding cells located at the North holding wing of the facility. This is somewhere near the front of the Detainment Facility.",	"task06_journal_entry_title":"Find the Imperial Officer",	"task07_journal_entry_description":"Give the officer the disguise you have.",	"task07_journal_entry_title":"Give the Officer the Disguise",	"task08_journal_entry_description":"n",	"task08_journal_entry_title":"n"
}}