{
	"stfFile":"quest/ground/u16_nym_themepark_nym_arena",
	"entries": {
		"category":"Nym's Theme Park",	"journal_entry_completion_summary":"You've bested all foes in Nym's Stronghold Arena.",	"journal_entry_description":"Beat all opponents in Nym's Stronghold Arena",	"journal_entry_title":"Beat Opponents in Arena",	"task00_journal_entry_description":"Find the roof of Nym's Stronghold and you will find the arena.",	"task00_journal_entry_title":"Find the Arena",	"task00_waypoint_name":"Nym's Stronghold Arena",	"task01_journal_entry_description":"Speak with the referee when you are ready for your first opponent.",	"task01_journal_entry_title":"Arena Referee",	"task01_retrieve_menu_text":"Call First Opponent",	"task01_start_message":"You hear someone approach.",	"task01_utterance_wave_1":"If I kill you, I get to live. You die now!",	"task01_waypoint_name":"Arena Referee",	"task02_comm_message_text":"You surprise me, fringer. Continue like this and you'll be a Lok Revenant in no time. Speak to the referee to start the next fight.",	"task03_journal_entry_description":"Speak to the referee when you are ready for your second opponent.",	"task03_journal_entry_title":"Second Opponent",	"task03_retrieve_menu_text":"Call Second Opponent",	"task03_start_message":"You hear something approach.",	"task03_utterance_wave_1":"Rrrrrr!",	"task03_waypoint_name":"Arena Referee",	"task04_comm_message_text":"Not too bad. When you're ready, speak to the referee to start your next fight.",	"task05_journal_entry_description":"Speak to the referee when you are ready for your next opponent.",	"task05_journal_entry_title":"Third Opponent",	"task05_retrieve_menu_text":"Call Third Opponent",	"task05_start_message":"You hear something approach.",	"task05_utterance_wave_1":"ROOOF! Grrrrrr!",	"task05_waypoint_name":"Arena Referee",	"task06_comm_message_text":"And another foe has fallen! You are the newest arena hero, congratulations! Speak to the referee to start the next fight.",	"task07_journal_entry_description":"Speak to the referee when you are ready for your next opponent.",	"task07_journal_entry_title":"Fourth Opponent",	"task07_retrieve_menu_text":"Call Fourth Opponent",	"task07_start_message":"You hear something approach.",	"task07_utterance_wave_1":"BZZZT!",	"task07_waypoint_name":"Arena Referee",	"task08_comm_message_text":"Great job! You've got one more fight left. Speak to the referee when ready.",	"task09_journal_entry_description":"Speak to the referee when you are ready for your next opponent.",	"task09_journal_entry_title":"Fifth Opponent",	"task09_retrieve_menu_text":"Call Final Opponent",	"task09_start_message":"You hear someone approach.",	"task09_utterance_wave_1":"Now you're mine! Ha ha.",	"task09_waypoint_name":"Arena Referee",	"task10_comm_message_text":"You did it! You just made me a much richer pirate. Ha ha!",	"task11_journal_entry_description":"Speak with Nym in the Stronghold.",	"task11_journal_entry_title":"Speak to Nym."
}}