{
	"stfFile":"quest/ground/yavin_fallenstar_pt3",
	"entries": {
		"category":"Yavin 4",	"journal_entry_description":"Your career as a Hutt enforcer is going well. Osae, the boss on Yavin 4, wants you to intercept a cargo ship carrying Death Star salvage. Once you have done so you need to force the ship back to land at a remote spot on Yavin IV where Osae is waiting with a team.",	"journal_entry_title":"Catch a Fallen Star Part 3",	"task00_journal_entry_description":"Intercept and escort a cargo ship back to Yavin 4 before it can jump out of the system. Once you have done so return to Osae for your reward.",	"task00_journal_entry_title":"Intercept Cargo Ship",	"task01_journal_entry_description":"The player has chosen to sell it to the Imperials.",	"task01_journal_entry_title":"Imperial Reward",	"task02_journal_entry_title":"Fallen Star Reward",	"task04_journal_entry_description":"The player choses to sell the cargo to the Rebels.",	"task04_journal_entry_title":"Rebel Choice",	"task05_journal_entry_title":"Fallen Star Reward",	"task06_journal_entry_title":"Fallen Star Completed",	"task07_journal_entry_description":"This is getting way to political. Tell Osae that you don't want to having anything more to do with her.",	"task07_journal_entry_title":"Walk away"
}}