{
	"stfFile":"spacequest/rescue/nova_intro_yavin_01",
	"entries": {
		"abort":"Wait, don't go!",	"arrival_phase_1":"Scanning area for Freighter",	"arrival_phase_2":"Freighter detected. Looks like it needs a little repair work.",	"assigned_delayed":"",	"attack_notify":"Incoming Hostiles, protect the freighter.",	"attack_stopped":"All Hostiles have been eliminated.",	"autorewardbody":"",	"autorewardfrom":"",	"autorewardsubject":"",	"complete":"Escort complete, freighter hyperspacing to Ord Mantell.",	"docking_complete":"Repairs complete.",	"docking_started":"Docking protocalls engaged.",	"failed_destroy":"Freighter destroyed, retreat.",	"panic_1":"Help me Pilot! I cannot take too many shots!",	"panic_2":"Pirates! They came back for me!",	"panic_3":"",	"panic_4":"",	"panic_5":"",	"quest_dock_d":"Use /dock to dock with the freighter. You need to get it repaired.",	"quest_dock_t":"Dock With the Damaged Freighter",	"quest_escort_d":"Now that the freighter has been repaired, you need to escort it the rest of the way to the hyperspace point.",	"quest_escort_t":"Escort the Repaired Freighter",	"quest_location_d":"Go to Yavin space.",	"quest_location_t":"Space Yavin",	"quest_update":"",	"recovery_success":"Thank you pilot, we can hyperspace out from here.",	"rescue_abandoned":"You can't just leave us here!",	"rescue_phase_1":"Thank you for coming, they damaged our reactor and we cannot leave.",	"rescue_phase_2":"Reactor repaired, thank you for your help. Please escort us out of here.",	"split_quest_alert":"",	"split_quest_alert_fail":"",	"taunt_1":"Where do you think you are going? Those supplies are ours!",	"taunt_2":"You foolish imbecile! You fell right into our trap.",	"taunt_3":"",	"taunt_4":"",	"taunt_5":"",	"thanks_1":"",	"thanks_2":"",	"thanks_3":"",	"thanks_4":"",	"thanks_5":"",	"title":"Rescue Nova Orion Freighter",	"title_d":"Nova Orion Industries has hired you to escort the damaged freighter back to safety."
}}