{
	"stfFile":"space/taunts/blackscale_hsskas",
	"entries": {
		"gothit1":"You fool! Don't you know who I am!",	"gothit2":"H'ssss",	"gothit3":"This is the end for you.",	"gothit4":"I have killed many a challenger, what is one more.",	"gothit5":"You will need to try harder than that.",	"hityou1":"Your time has come.",	"hityou2":"Feel the wrath of the Blackscale.",	"hityou3":"There will be no mercy for your kind.",	"hityou4":"I would bathe in your blood.",	"hityou5":"That cold grip around your heart is my claw.",	"entercombat1":"You have no chance.",	"entercombat2":"You have proven to be your own undoing.",	"entercombat3":"You are foolish to challenge us.",	"entercombat4":"I have you now, %NU!",	"entercombat5":"Easy prey.",	"death1":"Death comes for us all.",	"death2":"Aaarrrgh!",	"death3":"The Blackscale are eternal!",	"death4":"Hss'kor will overcome.",	"death5":"The Scorekeeper will judge me the victor."
}}